[
    {
    "id": 1,
    "name": "Square Shape Pre-Cut Hookah Foil with Pin - Afzal",
    "price": 150,
    "category": "Hookah",
    "image": "https://cdn.grofers.com/cdn-cgi/image/f=auto,fit=scale-down,q=70,metadata=none,w=270/layout-engine/2022-12/paan-corner_web.png",
    "timin": "21 min",
    "rating":3.9,
    "offer": 0
    
},
    {
    "id": 2,
    "name": "Premium Magic Coal By Stash Pro",
    "price": 140,
    "category": "Hookah",
    "image": "https://cdn.grofers.com/cdn-cgi/image/f=auto,fit=scale-down,q=70,metadata=none,w=270/layout-engine/2022-11/Slice-2_10.png",
    "timin": "22 min",
    "rating":4.5,
    "offer": 8
    
},
    {
    "id": 3,
    "name": "Kab's Jackpot Fiery and Crunchy Crisps",
    "price": 80,
    "category": "Hookah",
    "image": "https://cdn.grofers.com/cdn-cgi/image/f=auto,fit=scale-down,q=70,metadata=none,w=270/layout-engine/2022-11/Slice-3_9.png",
    "timin": "21 min",
    "rating":3.9,
    "offer": 0
    
},
{
"id": 4,
"name": "Kab's Jackpot Fiery and Crunchy Crisps",
"price": 80,
"category": "Hookah",
"image": "https://cdn.grofers.com/cdn-cgi/image/f=auto,fit=scale-down,q=70,metadata=none,w=270/layout-engine/2022-11/Slice-4_9.png",
"timin": "21 min",
"rating":3.9,
"offer": 0

},
{
"id": 5,
"name": "Kab's Jackpot Fiery and Crunchy Crisps",
"price": 80,
"category": "Hookah",
"image": "https://cdn.grofers.com/cdn-cgi/image/f=auto,fit=scale-down,q=70,metadata=none,w=270/layout-engine/2022-11/Slice-5_4.png",
"timin": "21 min",
"rating":3.9,
"offer": 0

},
{
"id": 6,
"name": "Kab's Jackpot Fiery and Crunchy Crisps",
"price": 80,
"category": "Hookah",
"image": "https://cdn.grofers.com/cdn-cgi/image/f=auto,fit=scale-down,q=70,metadata=none,w=270/layout-engine/2022-11/Slice-6_5.png",
"timin": "21 min",
"rating":3.9,
"offer": 0

},
{
"id": 7,
"name": "Kab's Jackpot Fiery and Crunchy Crisps",
"price": 80,
"category": "Hookah",
"image": "https://cdn.grofers.com/cdn-cgi/image/f=auto,fit=scale-down,q=70,metadata=none,w=270/layout-engine/2022-11/Slice-7_3.png",
"timin": "21 min",
"rating":3.9,
"offer": 0

},
{
"id": 8,
"name": "Kab's Jackpot Fiery and Crunchy Crisps",
"price": 80,
"category": "Hookah",
"image": "https://cdn.grofers.com/cdn-cgi/image/f=auto,fit=scale-down,q=70,metadata=none,w=270/layout-engine/2022-11/Slice-8_4.png",
"timin": "21 min",
"rating":3.9,
"offer": 0

},
{
"id": 9,
"name": "Kab's Jackpot Fiery and Crunchy Crisps",
"price": 80,
"category": "Hookah",
"image": "https://cdn.grofers.com/cdn-cgi/image/f=auto,fit=scale-down,q=70,metadata=none,w=270/layout-engine/2022-11/Slice-9_3.png",
"timin": "21 min",
"rating":3.9,
"offer": 0

},
{
"id": 10,
"name": "Kab's Jackpot Fiery and Crunchy Crisps",
"price": 80,
"category": "Hookah",
"image": "https://cdn.grofers.com/cdn-cgi/image/f=auto,fit=scale-down,q=70,metadata=none,w=270/layout-engine/2022-11/Slice-10.png",
"timin": "21 min",
"rating":3.9,
"offer": 0

},{
    "id": 11,
    "name": "Square Shape Pre-Cut Hookah Foil with Pin - Afzal",
    "price": 150,
    "category": "Hookah",
    "image": "https://cdn.grofers.com/cdn-cgi/image/f=auto,fit=scale-down,q=70,metadata=none,w=270/layout-engine/2022-11/Slice-11.png",
    "timin": "21 min",
    "rating":3.9,
    "offer": 0
    
},
    {
    "id": 12,
    "name": "Premium Magic Coal By Stash Pro",
    "price": 140,
    "category": "Hookah",
    "image": "https://cdn.grofers.com/cdn-cgi/image/f=auto,fit=scale-down,q=70,metadata=none,w=270/layout-engine/2022-11/Slice-12.png",
    "timin": "22 min",
    "rating":4.5,
    "offer": 8
    
},
    {
    "id": 13,
    "name": "Kab's Jackpot Fiery and Crunchy Crisps",
    "price": 80,
    "category": "Hookah",
    "image": "https://cdn.grofers.com/cdn-cgi/image/f=auto,fit=scale-down,q=70,metadata=none,w=270/layout-engine/2022-11/Slice-13.png",
    "timin": "21 min",
    "rating":3.9,
    "offer": 0
    
},
{
"id": 14,
"name": "Kab's Jackpot Fiery and Crunchy Crisps",
"price": 80,
"category": "Hookah",
"image": "https://cdn.grofers.com/cdn-cgi/image/f=auto,fit=scale-down,q=70,metadata=none,w=270/layout-engine/2022-11/Slice-14.png",
"timin": "21 min",
"rating":3.9,
"offer": 0

},
{
"id": 15,
"name": "Kab's Jackpot Fiery and Crunchy Crisps",
"price": 80,
"category": "Hookah",
"image": "https://cdn.grofers.com/cdn-cgi/image/f=auto,fit=scale-down,q=70,metadata=none,w=270/layout-engine/2022-11/Slice-15.png",
"timin": "21 min",
"rating":3.9,
"offer": 0

},
{
"id": 16,
"name": "Kab's Jackpot Fiery and Crunchy Crisps",
"price": 80,
"category": "Hookah",
"image": "https://cdn.grofers.com/cdn-cgi/image/f=auto,fit=scale-down,q=70,metadata=none,w=270/layout-engine/2022-11/Slice-16.png",
"timin": "21 min",
"rating":3.9,
"offer": 0

},
{
"id": 17,
"name": "Kab's Jackpot Fiery and Crunchy Crisps",
"price": 80,
"category": "Hookah",
"image": "https://cdn.grofers.com/cdn-cgi/image/f=auto,fit=scale-down,q=70,metadata=none,w=270/layout-engine/2022-11/Slice-17.png",
"timin": "21 min",
"rating":3.9,
"offer": 0

},
{
"id": 18,
"name": "Kab's Jackpot Fiery and Crunchy Crisps",
"price": 80,
"category": "Hookah",
"image": "https://cdn.grofers.com/cdn-cgi/image/f=auto,fit=scale-down,q=70,metadata=none,w=270/layout-engine/2022-11/Slice-18.png",
"timin": "21 min",
"rating":3.9,
"offer": 0

},
{
"id": 19,
"name": "Kab's Jackpot Fiery and Crunchy Crisps",
"price": 80,
"category": "Hookah",
"image": "https://cdn.grofers.com/cdn-cgi/image/f=auto,fit=scale-down,q=70,metadata=none,w=270/layout-engine/2022-11/Slice-19.png",
"timin": "21 min",
"rating":3.9,
"offer": 0

},
{
"id": 20,
"name": "Kab's Jackpot Fiery and Crunchy Crisps",
"price": 80,
"category": "Hookah",
"image": "https://cdn.grofers.com/cdn-cgi/image/f=auto,fit=scale-down,q=70,metadata=none,w=270/layout-engine/2022-11/Slice-20.png",
"timin": "21 min",
"rating":3.9,
"offer": 0

}
]